CHANGES.txt
LICENSE.txt
MANIFEST.in
README.rst
setup.py
dokku_client/__init__.py
dokku_client/client.py
dokku_client/command_tools.py
dokku_client.egg-info/PKG-INFO
dokku_client.egg-info/SOURCES.txt
dokku_client.egg-info/dependency_links.txt
dokku_client.egg-info/entry_points.txt
dokku_client.egg-info/requires.txt
dokku_client.egg-info/top_level.txt
dokku_client/commands/__init__.py
dokku_client/commands/config.py
dokku_client/commands/help.py
dokku_client/commands/prompt.py
dokku_client/commands/restart.py