Metadata-Version: 1.0
Name: dokku-client
Version: 0.2.2
Summary: Heroku-style command line interface for Dokku
Home-page: https://github.com/adamcharnock/dokku-client
Author: Adam Charnock
Author-email: adam@adamcharnock.com
License: MIT
Platform: UNKNOWN
